setup.py
mulpro/__init__.py
mulpro/log.py
mulpro/mulpro.py
mulpro.egg-info/PKG-INFO
mulpro.egg-info/SOURCES.txt
mulpro.egg-info/dependency_links.txt
mulpro.egg-info/top_level.txt