Metadata-Version: 1.1
Name: mulpro
Version: 0.1.6
Summary: Running any worker function in parallel and producing output in a separate process
Home-page: https://github.com/mhantke/mulpro
Author: Max F. Hantke
Author-email: maxhantke@gmail.com
License: UNKNOWN
Keywords: multiprocessing pipes parallel processes
Platform: UNKNOWN
Classifier: Development Status :: 3 - Alpha
Classifier: Intended Audience :: Science/Research
Classifier: Topic :: Scientific/Engineering :: Physics
Classifier: License :: OSI Approved :: BSD License
Classifier: Programming Language :: Python :: 2
Classifier: Programming Language :: Python :: 2.6
Classifier: Programming Language :: Python :: 2.7
